pkgtmpl/__init__.py
pkgtmpl/metadata.py
pkgtmpl/python/.gitignore
pkgtmpl/python/.travis.yml
pkgtmpl/python/CHANGELOG.md
pkgtmpl/python/CONTRIBUTORS.md
pkgtmpl/python/LICENSE
pkgtmpl/python/MANIFEST.in
pkgtmpl/python/README.md
pkgtmpl/python/TODO.md
pkgtmpl/python/_appname_.sublime-project
pkgtmpl/python/requirements.txt
pkgtmpl/python/requirements_test.txt
pkgtmpl/python/setup.py
pkgtmpl/python/tox.ini
pkgtmpl/python/_pkgname_/__init__.py
pkgtmpl/python/_pkgname_/metadata.py
pkgtmpl/python/_pkgname_/tests.py
pkgtmpl-0.2.6.dist-info/DESCRIPTION.rst
pkgtmpl-0.2.6.dist-info/METADATA
pkgtmpl-0.2.6.dist-info/RECORD
pkgtmpl-0.2.6.dist-info/WHEEL
pkgtmpl-0.2.6.dist-info/entry_points.txt
pkgtmpl-0.2.6.dist-info/metadata.json
pkgtmpl-0.2.6.dist-info/top_level.txt
