Metadata-Version: 2.0
Name: pkgtmpl
Version: 0.2.6
Summary: Bootstrap python packages with sane defaults
Home-page: https://github.com/jmagnusson/pkgtmpl
Author: Jacob Magnusson
Author-email: m@jacobian.se
License: BSD
Platform: unix
Platform: macos
Classifier: Development Status :: 3 - Alpha
Classifier: Intended Audience :: Developers
Classifier: License :: OSI Approved :: BSD License
Classifier: Operating System :: Unix
Classifier: Operating System :: MacOS :: MacOS X
Classifier: Programming Language :: Python
Requires-Dist: Jinja2 (>=2.7.1)
